docs/source/conf.py
examples/prax_backend_example.py
rompy_oceanum/__init__.py
rompy_oceanum/cli.py
rompy_oceanum/client.py
rompy_oceanum/config.py
rompy_oceanum/datamesh.py
rompy_oceanum/pipeline.py
rompy_oceanum/postprocess.py
rompy_oceanum/prax_client.py
rompy_oceanum/cli/__init__.py
rompy_oceanum/cli/main.py
rompy_oceanum/cli/rompy/__init__.py
rompy_oceanum/cli/rompy/create.py
rompy_oceanum/cli/rompy/delete.py
rompy_oceanum/cli/rompy/describe.py
rompy_oceanum/cli/rompy/init.py
rompy_oceanum/cli/rompy/list.py
rompy_oceanum/cli/rompy/logs.py
rompy_oceanum/cli/rompy/main.py
rompy_oceanum/cli/rompy/pipeline_crud.py
rompy_oceanum/cli/rompy/project_crud.py
rompy_oceanum/cli/rompy/run.py
rompy_oceanum/cli/rompy/status.py
rompy_oceanum/cli/rompy/sync.py
rompy_oceanum/pipeline_templates/swan.yaml
scripts/release.py
tests/__init__.py
tests/conftest.py
tests/test_config.py
tests/test_integration.py
tests/test_pipeline.py
tests/test_postprocess.py
tests/test_prax_client.py
tests/test_prax_result.py
rompy_oceanum-0.1.11.dist-info/METADATA
rompy_oceanum-0.1.11.dist-info/WHEEL
rompy_oceanum-0.1.11.dist-info/entry_points.txt
rompy_oceanum-0.1.11.dist-info/top_level.txt
rompy_oceanum-0.1.11.dist-info/RECORD
