Metadata-Version: 2.4
Name: rompy-oceanum
Version: 0.1.11
Summary: Oceanum Prax pipeline integration for rompy with Prax specification templates
Author: rompy-oceanum contributors
Project-URL: Homepage, https://github.com/rom-py/rompy
Project-URL: Bug Tracker, https://github.com/rom-py/rompy/issues
Classifier: Programming Language :: Python :: 3
Classifier: License :: OSI Approved :: MIT License
Classifier: Operating System :: OS Independent
Requires-Python: >=3.8
Requires-Dist: rompy>=0.6.1
Requires-Dist: rompy-swan>=0.6.0
Requires-Dist: rompy-schism>=0.6.0
Requires-Dist: pydantic>=2.0.0
Requires-Dist: pyyaml>=6.0
Requires-Dist: oceanum>=1.0.11
Requires-Dist: oceanum-prax>=0.1.0
Requires-Dist: tenacity
Provides-Extra: dev
Requires-Dist: pytest>=6.0.0; extra == "dev"
Requires-Dist: pytest-cov>=2.12.0; extra == "dev"
Requires-Dist: pytest-mock>=3.6.0; extra == "dev"
Requires-Dist: tbump; extra == "dev"
Provides-Extra: docs
Requires-Dist: sphinx>=7.0.0; extra == "docs"
Requires-Dist: sphinx-rtd-theme>=1.3.0; extra == "docs"
Requires-Dist: sphinx-autodoc-typehints>=1.24.0; extra == "docs"
Requires-Dist: myst-parser>=2.0.0; extra == "docs"
Requires-Dist: sphinx-copybutton>=0.5.2; extra == "docs"
Requires-Dist: sphinx-autoapi>=3.0.0; extra == "docs"
Requires-Dist: sphinxext-opengraph>=0.8.2; extra == "docs"
Requires-Dist: sphinx-design>=0.5.0; extra == "docs"
